cmdbin/__init__.py
cmdbin/__main__.py
cmdbin/v1.py
cmdbin-1.0.0.dist-info/LICENSE
cmdbin-1.0.0.dist-info/METADATA
cmdbin-1.0.0.dist-info/WHEEL
cmdbin-1.0.0.dist-info/entry_points.txt
cmdbin-1.0.0.dist-info/top_level.txt
cmdbin-1.0.0.dist-info/RECORD
