Metadata-Version: 2.1
Name: cmdbin
Version: 1.0.0
Summary: cli for uploading to cmdbin.cc
Author-email: Luke Schwager <luke@blucobalt.dev>
License: BSD 3-Clause License
Project-URL: Homepage, https://github.com/blucobalt/cmdbin.py
Project-URL: Bug Tracker, https://github.com/blucobalt/cmdbin.py/issues
Classifier: Programming Language :: Python :: 3
Classifier: Operating System :: OS Independent
Requires-Python: >=3.5
License-File: LICENSE
Requires-Dist: requests
